Workbook

Sheet Balance Sheet
A1: Bharat Heavy Electricals Limited - Consolidated Balance Sheet
A2: As at March 31
A3: (₹ in Crore)
B4: Particulars | D4: As at Mar 31, 2021 | E4: As at Mar 31, 2022 | F4: As at Mar 31, 2023 | G4: As at Mar 31, 2024
B5: ASSETS
B6: Non-current assets
B7: Property, plant and equipment | D7: 2428.98 | E7: 2336.34 | F7: 2408.74 | G7: 2510.69
B8: Capital work-in-progress | D8: 403.21 | E8: 422.32 | F8: 344.59 | G8: 282.32
B9: Intangible assets | D9: 62.16 | E9: 62.12 | F9: 67.24 | G9: 63.35
B10: Intangible assets under development | D10: 16.35 | E10: 8.66 | F10: 9.26 | G10: 26.04
B11: Investment accounted for using equity method | D11: 181.76 | E11: 201.86 | F11: 232.29 | G11: 254.48
B12: Financial assets:
B13: Investments (NC) | D13: 3.58 | E13: 3.29 | F13: 3.13 | G13: 1.19
B14: Trade receivables (NC)` | D14: 3179.74 | E14: 3203.84 | F14: 3415.54 | G14: 3224.69
B15: Other financial assets (NC) | D15: 97.39 | E15: 86.73 | F15: 83.96 | G15: 206.1
B16: Total financial assets (NC) | D16: 3280.71 | E16: 3293.86 | F16: 3502.63 | G16: 3431.98
B17: Deferred tax assets (net) | D17: 3671.24 | E17: 3530.08 | F17: 3422.62 | G17: 4201.26
B18: Other non-current assets | D18: 16852.44 | E18: 18526.54 | F18: 19300.14 | G18: 13689.69
B19: Total non-current assets | D19: 26896.85 | E19: 28381.78 | F19: 29287.51 | G19: 24459.81
B20: Current assets
B21: Inventories | D21: 7194.45 | E21: 6560.21 | F21: 6755.9 | G21: 7220.57
B22: Financial assets:
B23: Trade receivables (Current) | D23: 4035.07 | E23: 3024.75 | F23: 3128.35 | G23: 4785.38
B24: Cash and cash equivalents | D24: 1527.19 | E24: 732.62 | F24: 1560.52 | G24: 1835.04
B25: Bank balances other than cash and cash equivalents | D25: 5174.26 | E25: 6421.07 | F25: 5082.06 | G25: 4322.43
B26: Other financial assets (Current) | D26: 232.65 | E26: 211.56 | F26: 278.23 | G26: 239.82
B27: Total financial assets (Current) | D27: 10969.17 | E27: 10390 | F27: 10049.16 | G27: 11182.67
B28: Current tax assets (net) | D28: 403.6 | E28: 119.24 | F28: 226.38 | G28: 229.07
B29: Other current assets | D29: 9776.14 | E29: 10792.53 | F29: 13050.84 | G29: 15913.38
B30: Total current assets | D30: 28343.36 | E30: 27861.98 | F30: 30082.28 | G30: 34545.69
B31: TOTAL ASSETS | D31: 55240.21 | E31: 56243.76 | F31: 59369.79 | G31: 59005.5
B32: EQUITY AND LIABILITIES
B33: Equity
B34: Equity share capital | D34: 696.41 | E34: 696.41 | F34: 696.41 | G34: 696.41
B35: Other equity | D35: 25287.25 | E35: 25810.19 | F35: 26131.62 | G35: 23742.24
B36: Total equity | D36: 25972 | E36: 26506.6 | F36: 26828.03 | G36: 24438.65
B37: Non-current liabilities
B38: Financial liabilities:
B39: Lease Liabilities (NC) | D39: 53.41 | E39: 35.12 | F39: 33.75 | G39: 23.55
B40: Trade payables (NC) - MSME | D40: 157.92 | E40: 127.45 | F40: 128.11
B41: Trade payables (NC) - Others | D41: 1725.85 | E41: 2004.48 | F41: 2065.92 | G41: 2292.76
B42: Other financial liabilities (NC) | D42: 216.72 | E42: 215.1 | F42: 255.7 | G42: 325.88
B43: Total financial liabilities (NC) | D43: 2153.9 | E43: 2382.15 | F43: 2483.48 | G43: 2642.19
B44: Provisions (NC) | D44: 3925.56 | E44: 3771.21 | F44: 4101.02 | G44: 2489.08
B45: Other non-current liabilities | D45: 2831.54 | E45: 2212.65 | F45: 2605.81 | G45: 4102.77
B46: Total non-current liabilities | D46: 8911 | E46: 8366.01 | F46: 9190.31 | G46: 9234.04
B47: Current liabilities
B48: Financial liabilities:
B49: Borrowings | D49: 4849.28 | E49: 4745 | F49: 5385 | G49: 8808
B50: Lease Liabilities (Current) | D50: 48.2 | E50: 49.81 | F50: 34.76 | G50: 24.91
B51: Trade payables (Current) - MSME | D51: 751.57 | E51: 745.82 | F51: 1211.53 | G51: 1157.45
B52: Trade payables (Current) - Others | D52: 5929.26 | E52: 7003.77 | F52: 8684.3 | G52: 7538.79
B53: Other financial liabilities (Current) | D53: 929.58 | E53: 1124.09 | F53: 1276.93 | G53: 1418.44
B54: Total financial liabilities (Current) | D54: 12507.89 | E54: 13668.49 | F54: 16592.52 | G54: 18947.59
B55: Provisions (Current) | D55: 3168.52 | E55: 3066.7 | F55: 2796.63 | G55: 2318.27
B56: Other current liabilities | D56: 4680.8 | E56: 4635.96 | F56: 3962.29 | G56: 4066.94
B57: Total current liabilities | D57: 20357.21 | E57: 21371.15 | F57: 23351.44 | G57: 25332.8
B58: Total liabilities | D58: 29268.21 | E58: 29737.16 | F58: 32541.75 | G58: 34566.84
B59: TOTAL EQUITY AND LIABILITIES | D59: 55240.21 | E59: 56243.76 | F59: 59369.79 | G59: 59005.5

Sheet P&L
A1: Bharat Heavy Electricals Limited - Consolidated Statement of Profit and Loss
A2: For the year ended March 31
A3: (₹ in Crore)
B4: Particulars | D4: FY ended Mar 31, 2021 | E4: FY ended Mar 31, 2022 | F4: FY ended Mar 31, 2023 | G4: FY ended Mar 31, 2024
B5: INCOME
B6: Revenue from operations | D6: 17308.69 | E6: 21211.09 | F6: 23364.94 | G6: 23892.78
B7: Other income | D7: 348.42 | E7: 354.54 | F7: 488.63 | G7: 546.27
B8: TOTAL INCOME | D8: 17657.11 | E8: 21565.63 | F8: 23853.57 | G8: 24439.05
B9: EXPENSES
B10: Cost of raw materials consumed | D10: 4346.62 | E10: 5055.63 | F10: 5875.28 | G10: 6116.27
B11: Purchases of Bought out items | D11: 3811.94 | E11: 4141.75 | F11: 4657.33 | G11: 5868.46
B12: Civil, erection and engineering expenses | D12: 2912.47 | E12: 4792.61 | F12: 5421.08 | G12: 4908.84
B13: Consumption of stores & spares | D13: 288.74 | E13: 271.44 | F13: 404.18 | G13: 350.28
B14: Changes in inventories of finished goods, WIP and Scrap | D14: 510.86 | E14: 532.41 | F14: -57.15 | G14: -436.74
B15: Employee benefits expense | D15: 5378.15 | E15: 5519.05 | F15: 5700.63 | G15: 5628.84
B16: Other Expenses | D16: 3201.2 | E16: 162.62 | F16: 647.03 | G16: 844.23
B17: Finance costs | D17: 373.95 | E17: 355.96 | F17: 521.43 | G17: 731.29
B18: Depreciation & amortisation expense | D18: 473.25 | E18: 314.12 | F18: 260.34 | G18: 248.9
B19: TOTAL EXPENSES | D19: 21297.18 | E19: 21145.59 | F19: 23430.15 | G19: 24260.37
B20: Profit / (loss) before share of JV and tax | D20: -3640.07 | E20: 420.04 | F20: 423.42 | G20: 178.68
B21: Share of net profit / (loss) of JV (equity method) | D21: 44.14 | E21: 50.42 | F21: 56.02 | G21: 63.98
B22: PROFIT BEFORE TAX | D22: -3595.93 | E22: 470.46 | F22: 479.44 | G22: 242.66
B23: Tax expenses
B24: Current tax | D24: 15.82 | E24: -77.13 | F24: -111.22 | G24: -112.56
B25: Deferred tax | D25: -912.05 | E25: 102.88 | F25: 113.27 | G25: 73
B26: Total tax expense | D26: -896.23 | E26: 25.75 | F26: 2.05 | G26: -39.56
B27: PROFIT FOR THE YEAR (A) | D27: -2699.7 | E27: 444.71 | F27: 477.39 | G27: 282.22
B28: OTHER COMPREHENSIVE INCOME
B29: Items that will not be reclassified to profit or loss (net of tax)
B30: Remeasurement of defined employee benefits | D30: 19.98 | E30: 76.87 | F30: -17.27 | G30: -82.41
B31: Share of OCI of JV accounted using equity method | D31: 0.07 | E31: 0.03 | F31: 0.59 | G31: -0.14
B32: OTHER COMPREHENSIVE INCOME FOR THE YEAR (B) | D32: 20.05 | E32: 76.9 | F32: -16.68 | G32: -82.55
B33: TOTAL COMPREHENSIVE INCOME FOR THE YEAR (A+B) | D33: -2679.65 | E33: 521.61 | F33: 460.71 | G33: 199.67
B34: Earnings per equity share (Face value of Rs 2 each)
B35: Basic | D35: -7.75 | E35: 1.28 | F35: 1.37 | G35: 0.81
B36: Diluted | D36: -7.75 | E36: 1.28 | F36: 1.37 | G36: 0.81

Sheet Cash Flow
A1: Bharat Heavy Electricals Limited - Consolidated Statement of Cash Flows
A2: For the year ended March 31
A3: (₹ in Crore)
B4: Particulars | D4: FY ended Mar 31, 2021 | E4: FY ended Mar 31, 2022 | F4: FY ended Mar 31, 2023 | G4: FY ended Mar 31, 2024
B5: A. CASH FLOW FROM OPERATING ACTIVITIES
B6: Profit / (Loss) before tax | D6: -3595.93 | E6: 470.46 | F6: 479.44 | G6: 242.66
B7: Adjustments for:
B8: Provision and write off | D8: 1241.08 | E8: -1120.06 | F8: -86.31 | G8: -1188.18
B9: Depreciation and amortisation | D9: 473.25 | E9: 314.12 | F9: 260.34 | G9: 248.9
B10: Finance cost (including unwinding of interest) | D10: 373.95 | E10: 355.96 | F10: 521.43 | G10: 731.29
B11: Interest & dividend income | D11: -320.86 | E11: -302.79 | F11: -421.12 | G11: -493.78
B12: Share of loss / (profit) in joint venture | D12: -44.14 | E12: -50.42 | F12: -56.02 | G12: -63.98
B13: Divestment of stake in subsidiary | E13: -17.08 | F13: 0
B14: Unrealised Foreign Exchange loss / (gain) | D14: 5.8 | E14: 19.26 | F14: -401.85 | G14: 56.03
B15: Amortisation of Government Grant | F15: -8.9 | G15: -15.62
B16: Others | D16: -3.79 | E16: -6.61 | F16: -33.02 | G16: -7.78
B17: Cash generated / (used) in operations before working capital changes | D17: -1870.64 | E17: -337.16 | F17: 253.99 | G17: -490.46
B18: Adjustment for changes in working capital:
B19: Trade Receivables | D19: 4014.8 | E19: 1881.12 | F19: 92.04 | G19: -2469.24
B20: Contract Assets | D20: -1310.61 | E20: -2594.15 | F20: -2370.65 | G20: -13.7
B21: Inventories | D21: 1536.71 | E21: 603.4 | F21: -192.4 | G21: -503.04
B22: Loans, advances & other assets | D22: -246.86 | E22: 143.49 | F22: -262.28 | G22: -740.8
B23: Sub total (Assets side) | D23: 3994.04 | E23: 33.86 | F23: -2733.29 | G23: -3726.78
B24: Trade payable | D24: -1305.4 | E24: 1300.96 | F24: 2103.68 | G24: -962.56
B25: Advances from customers, deposits and others | D25: -94.08 | E25: -387.69 | F25: -167.84 | G25: 1244.73
B26: Provisions | D26: 26.38 | E26: -358.6 | F26: -308.48
B27: Sub total (Liabilities side) | D27: -1373.1 | E27: 554.67 | F27: 1627.36 | G27: 282.17
B28: Net cash (used in) / from working capital | D28: 2620.94 | E28: 588.53 | F28: -1105.93 | G28: -3444.61
B29: Cash generated / (used) in operations | D29: 750.3 | E29: 251.37 | F29: -851.94 | G29: -3935.07
B30: Income taxes paid | D30: -216.65 | E30: -258 | F30: -155.54 | G30: -158.48
B31: Refund of income taxes | D31: 26.3 | E31: 666.88 | F31: 265.96 | G31: 380.65
B32: Net cash (used in) / from operating activities | D32: 559.95 | E32: 660.25 | F32: -741.52 | G32: -3712.9
B33: B. CASH FLOW FROM INVESTING ACTIVITIES
B34: Redemption / maturity of bank deposits (orig. maturity > 3 months) | D34: -159.98 | E34: -1251.12 | F34: 1358.78 | G34: 1112.69
B35: Interest received | D35: 343.11 | E35: 257.93 | F35: 250.72 | G35: 399.3
B36: Income received from mutual funds | D36: 1.42
B37: Sale proceeds from Investment | F37: 25.42 | G37: 0.8
B38: Dividend received from joint ventures | D38: 21.42 | E38: 30.35 | F38: 26.18 | G38: 41.65
B39: Sale of PPE & Intangible Assets | D39: 1.88 | E39: 6.9 | F39: 7.76 | G39: 8.92
B40: Purchase of PPE & Intangible Assets | D40: -250.35 | E40: -169.38 | F40: -188.4 | G40: -232.5
B41: Net cash (used in) / from investing activities | D41: -42.5 | E41: -1125.32 | F41: 1480.46 | G41: 1330.86
B42: C. CASH FLOW FROM FINANCING ACTIVITIES
B43: Proceeds from short term borrowings | D43: -98.01 | E43: -87.53 | F43: 640 | G43: 3423
B44: Repayment of lease obligation (Principal) | D44: -60.3 | E44: -48.79 | F44: -49.77 | G44: -34.32
B45: Repayment of lease obligation (Interest) | D45: -12.95 | E45: -9.57 | F45: -7.27 | G45: -4.73
B46: Dividend paid | D46: -0.68 | E46: -0.3 | F46: -139.18 | G46: -139.45
B47: Interest paid | D47: -222.21 | E47: -183.3 | F47: -354.82 | G47: -588.76
B48: Net cash (used in) / from financing activities | D48: -394.15 | E48: -329.49 | F48: 88.96 | G48: 2655.74
B49: D. Net increase / (decrease) in cash and cash equivalents | D49: 123.3 | E49: -794.56 | F49: 827.9 | G49: 273.7
B50: Opening balance of cash and cash equivalents (excl. cash credit of subsidiary) | D50: 1396.6 | E50: 1519.9 | F50: 732.62 | G50: 1561.34
B51: Adjustment of Cash credit of subsidiary | D51: 0 | E51: 7.28 | F51: 0
B52: Closing balance of cash and cash equivalents | D52: 1519.9 | E52: 732.62 | F52: 1560.52 | G52: 1835.04

Sheet Detailed Analysis
B1: Bharat Heavy Electricals Limited - Detailed Financial Analysis
C2: Consolidated FY2021-FY2024 | All figures in INR Crore
C4: Particulars | D4: Source / Definition | E4: FY2021 | F4: FY2022 | G4: FY2023 | H4: FY2024 | I4: FY2025E | J4: FY2026E | K4: FY2027E | L4: FY2028E | M4: FY2029E
C5: 1. INCOME STATEMENT & PROFITABILITY
C6: Revenue from operations | D6: P&L row 6 | E6: ='P&L'!D6 -> 17308.69 | F6: ='P&L'!E6 -> 21211.09 | G6: ='P&L'!F6 -> 23364.94 | H6: ='P&L'!G6 -> 23892.78 | I6: =H6*(1+I108) -> 25804.202 | J6: =I6*(1+J108) -> 27868.539 | K6: =J6*(1+K108) -> 29819.336 | L6: =K6*(1+L108) -> 31906.69 | M6: =L6*(1+M108) -> 33821.091
C7: Revenue growth (YoY) | D7: (Current / Prior) - 1 | F7: =F6/E6-1 -> 0.225459 | G7: =G6/F6-1 -> 0.10154358 | H7: =H6/G6-1 -> 0.022591113 | I7: =I6/H6-1 -> 0.08 | J7: =J6/I6-1 -> 0.08 | K7: =K6/J6-1 -> 0.07 | L7: =L6/K6-1 -> 0.07 | M7: =M6/L6-1 -> 0.06
C8: Other income | D8: P&L row 7 | E8: ='P&L'!D7 -> 348.42 | F8: ='P&L'!E7 -> 354.54 | G8: ='P&L'!F7 -> 488.63 | H8: ='P&L'!G7 -> 546.27 | I8: =I6*I112 -> 516.08405 | J8: =J6*J112 -> 557.37077 | K8: =K6*K112 -> 596.38673 | L8: =L6*L112 -> 638.1338 | M8: =M6*M112 -> 676.42182
C9: Total income | D9: P&L row 8 | E9: ='P&L'!D8 -> 17657.11 | F9: ='P&L'!E8 -> 21565.63 | G9: ='P&L'!F8 -> 23853.57 | H9: ='P&L'!G8 -> 24439.05 | I9: =I6+I8 -> 26320.286 | J9: =J6+J8 -> 28425.909 | K9: =K6+K8 -> 30415.723 | L9: =L6+L8 -> 32544.824 | M9: =M6+M8 -> 34497.513
C10: Total income growth (YoY) | D10: (Current / Prior) - 1 | F10: =F9/E9-1 -> 0.22135672 | G10: =G9/F9-1 -> 0.10609196 | H10: =H9/G9-1 -> 0.024544754 | I10: =I9/H9-1 -> 0.07697666 | J10: =J9/I9-1 -> 0.08 | K10: =K9/J9-1 -> 0.07 | L10: =L9/K9-1 -> 0.07 | M10: =M9/L9-1 -> 0.06
C11: Less: Material & direct costs | D11: P&L rows 10-14 | E11: ='P&L'!D10+'P&L'!D11+'P&L'!D12+'P&L'!D13+'P&L'!D14 -> 11870.63 | F11: ='P&L'!E10+'P&L'!E11+'P&L'!E12+'P&L'!E13+'P&L'!E14 -> 14793.84 | G11: ='P&L'!F10+'P&L'!F11+'P&L'!F12+'P&L'!F13+'P&L'!F14 -> 16300.72 | H11: ='P&L'!G10+'P&L'!G11+'P&L'!G12+'P&L'!G13+'P&L'!G14 -> 16807.11 | I11: =I6-I12 -> 18062.942 | J11: =J6-J12 -> 19507.977 | K11: =K6-K12 -> 20873.535 | L11: =L6-L12 -> 22334.683 | M11: =M6-M12 -> 23674.764
C12: Gross profit | D12: Revenue - Material & direct costs | E12: =E6-E11 -> 5438.06 | F12: =F6-F11 -> 6417.25 | G12: =G6-G11 -> 7064.22 | H12: =H6-H11 -> 7085.67 | I12: =I6*I111 -> 7741.2607 | J12: =J6*J111 -> 8360.5616 | K12: =K6*K111 -> 8945.8009 | L12: =L6*L111 -> 9572.007 | M12: =M6*M111 -> 10146.327
C13: Gross margin | D13: Gross profit / Revenue | E13: =E12/E6 -> 0.31418091 | F13: =F12/F6 -> 0.30254221 | G13: =G12/G6 -> 0.30234274 | H13: =H12/H6 -> 0.29656114 | I13: =I12/I6 -> 0.3 | J13: =J12/J6 -> 0.3 | K13: =K12/K6 -> 0.3 | L13: =L12/L6 -> 0.3 | M13: =M12/M6 -> 0.3
C14: Less: Employee benefits expense | D14: P&L row 15 | E14: ='P&L'!D15 -> 5378.15 | F14: ='P&L'!E15 -> 5519.05 | G14: ='P&L'!F15 -> 5700.63 | H14: ='P&L'!G15 -> 5628.84 | I14: =I6*I113 -> 6322.0296 | J14: =J6*J113 -> 6827.792 | K14: =K6*K113 -> 7305.7374 | L14: =L6*L113 -> 7817.139 | M14: =M6*M113 -> 8286.1673
C15: Less: Other expenses | D15: P&L row 16 | E15: ='P&L'!D16 -> 3201.2 | F15: ='P&L'!E16 -> 162.62 | G15: ='P&L'!F16 -> 647.03 | H15: ='P&L'!G16 -> 844.23 | I15: =I6*I114 -> 645.10506 | J15: =J6*J114 -> 696.71346 | K15: =K6*K114 -> 745.48341 | L15: =L6*L114 -> 797.66725 | M15: =M6*M114 -> 845.52728
C16: EBITDA | D16: PBT + Finance + D&A | E16: ='P&L'!D22+'P&L'!D17+'P&L'!D18 -> -2748.73 | F16: ='P&L'!E22+'P&L'!E17+'P&L'!E18 -> 1140.54 | G16: ='P&L'!F22+'P&L'!F17+'P&L'!F18 -> 1261.21 | H16: ='P&L'!G22+'P&L'!G17+'P&L'!G18 -> 1222.85 | I16: =I12+I8-I14-I15 -> 1290.2101 | J16: =J12+J8-J14-J15 -> 1393.4269 | K16: =K12+K8-K14-K15 -> 1490.9668 | L16: =L12+L8-L14-L15 -> 1595.3345 | M16: =M12+M8-M14-M15 -> 1691.0546
C17: EBITDA margin | D17: EBITDA / Revenue | E17: =E16/E6 -> -0.15880636 | F17: =F16/F6 -> 0.053770928 | G17: =G16/G6 -> 0.053978739 | H17: =H16/H6 -> 0.051180733 | I17: =I16/I6 -> 0.05 | J17: =J16/J6 -> 0.05 | K17: =K16/K6 -> 0.05 | L17: =L16/L6 -> 0.05 | M17: =M16/M6 -> 0.05
C18: Less: Depreciation & amortisation | D18: P&L row 18 | E18: ='P&L'!D18 -> 473.25 | F18: ='P&L'!E18 -> 314.12 | G18: ='P&L'!F18 -> 260.34 | H18: ='P&L'!G18 -> 248.9 | I18: =I6*I115 -> 309.65043 | J18: =J6*J115 -> 334.42246 | K18: =K6*K115 -> 357.83204 | L18: =L6*L115 -> 382.88028 | M18: =M6*M115 -> 405.85309
C19: EBIT | D19: EBITDA - D&A | E19: =E16-E18 -> -3221.98 | F19: =F16-F18 -> 826.42 | G19: =G16-G18 -> 1000.87 | H19: =H16-H18 -> 973.95 | I19: =I16-I18 -> 980.55969 | J19: =J16-J18 -> 1059.0045 | K19: =K16-K18 -> 1133.1348 | L19: =L16-L18 -> 1212.4542 | M19: =M16-M18 -> 1285.2015
C20: EBIT margin | D20: EBIT / Revenue | E20: =E19/E6 -> -0.18614811 | F20: =F19/F6 -> 0.038961694 | G20: =G19/G6 -> 0.042836404 | H20: =H19/H6 -> 0.04076336 | I20: =I19/I6 -> 0.038 | J20: =J19/J6 -> 0.038 | K20: =K19/K6 -> 0.038 | L20: =L19/L6 -> 0.038 | M20: =M19/M6 -> 0.038
C21: Less: Finance costs | D21: P&L row 17 | E21: ='P&L'!D17 -> 373.95 | F21: ='P&L'!E17 -> 355.96 | G21: ='P&L'!F17 -> 521.43 | H21: ='P&L'!G17 -> 731.29 | I21: =I6*I116 -> 645.10506 | J21: =J6*J116 -> 696.71346 | K21: =K6*K116 -> 745.48341 | L21: =L6*L116 -> 797.66725 | M21: =M6*M116 -> 845.52728
C22: Profit before tax (PBT) | D22: P&L row 22 | E22: ='P&L'!D22 -> -3595.93 | F22: ='P&L'!E22 -> 470.46 | G22: ='P&L'!F22 -> 479.44 | H22: ='P&L'!G22 -> 242.66 | I22: =I19-I21 -> 335.45463 | J22: =J19-J21 -> 362.291 | K22: =K19-K21 -> 387.65137 | L22: =L19-L21 -> 414.78697 | M22: =M19-M21 -> 439.67419
C23: PBT margin | D23: PBT / Revenue | E23: =E22/E6 -> -0.20775287 | F23: =F22/F6 -> 0.022179907 | G23: =G22/G6 -> 0.020519633 | H23: =H22/H6 -> 0.010156206 | I23: =I22/I6 -> 0.013 | J23: =J22/J6 -> 0.013 | K23: =K22/K6 -> 0.013 | L23: =L22/L6 -> 0.013 | M23: =M22/M6 -> 0.013
C24: Less: Total tax expense | D24: P&L row 26 | E24: ='P&L'!D26 -> -896.23 | F24: ='P&L'!E26 -> 25.75 | G24: ='P&L'!F26 -> 2.05 | H24: ='P&L'!G26 -> -39.56 | I24: =I22*I117 -> 83.863658 | J24: =J22*J117 -> 90.57275 | K24: =K22*K117 -> 96.912843 | L24: =L22*L117 -> 103.69674 | M24: =M22*M117 -> 109.91855
C25: Effective tax rate | D25: Tax / PBT | E25: =E24/E22 -> 0.24923455 | F25: =F24/F22 -> 0.054733665 | G25: =G24/G22 -> 0.0042758218 | H25: =H24/H22 -> -0.16302646 | I25: =I24/I22 -> 0.25 | J25: =J24/J22 -> 0.25 | K25: =K24/K22 -> 0.25 | L25: =L24/L22 -> 0.25 | M25: =M24/M22 -> 0.25
C26: Profit after tax (PAT) | D26: P&L row 27 | E26: ='P&L'!D27 -> -2699.7 | F26: ='P&L'!E27 -> 444.71 | G26: ='P&L'!F27 -> 477.39 | H26: ='P&L'!G27 -> 282.22 | I26: =I22-I24 -> 251.59097 | J26: =J22-J24 -> 271.71825 | K26: =K22-K24 -> 290.73853 | L26: =L22-L24 -> 311.09023 | M26: =M22-M24 -> 329.75564
C27: PAT margin | D27: PAT / Revenue | E27: =E26/E6 -> -0.15597368 | F27: =F26/F6 -> 0.020965919 | G27: =G26/G6 -> 0.020431895 | H27: =H26/H6 -> 0.011811936 | I27: =I26/I6 -> 0.00975 | J27: =J26/J6 -> 0.00975 | K27: =K26/K6 -> 0.00975 | L27: =L26/L6 -> 0.00975 | M27: =M26/M6 -> 0.00975
C29: 2. BALANCE SHEET SNAPSHOT
C30: Total assets | D30: Balance Sheet row 31 | E30: ='Balance Sheet'!D31 -> 55240.21 | F30: ='Balance Sheet'!E31 -> 56243.76 | G30: ='Balance Sheet'!F31 -> 59369.79 | H30: ='Balance Sheet'!G31 -> 59005.5 | I30: =I32+I34 -> 61254.841 | J30: =J32+J34 -> 64198.444 | K30: =K32+K34 -> 66980.148 | L30: =L32+L34 -> 69956.571 | M30: =M32+M34 -> 72686.377
C31: Asset growth (YoY) | D31: (Current / Prior) - 1 | F31: =F30/E30-1 -> 0.01816702 | G31: =G30/F30-1 -> 0.055580032 | H31: =H30/G30-1 -> -0.0061359489 | I31: =I30/H30-1 -> 0.03812087 | J31: =J30/I30-1 -> 0.048055018 | K31: =K30/J30-1 -> 0.043329779 | L31: =L30/K30-1 -> 0.0444374 | M31: =M30/L30-1 -> 0.039021433
C32: Non-current assets | D32: Balance Sheet row 19 | E32: ='Balance Sheet'!D19 -> 26896.85 | F32: ='Balance Sheet'!E19 -> 28381.78 | G32: ='Balance Sheet'!F19 -> 29287.51 | H32: ='Balance Sheet'!G19 -> 24459.81 | I32: =H32*(1+I127) -> 24459.81 | J32: =I32*(1+J127) -> 24459.81 | K32: =J32*(1+K127) -> 24459.81 | L32: =K32*(1+L127) -> 24459.81 | M32: =L32*(1+M127) -> 24459.81
C33: % of total assets | D33: NC assets / Total assets | E33: =E32/E30 -> 0.48690709 | F33: =F32/F30 -> 0.50462096 | G33: =G32/G30 -> 0.49330661 | H33: =H32/H30 -> 0.41453441 | I33: =I32/I30 -> 0.39931228 | J33: =J32/J30 -> 0.38100316 | K33: =K32/K30 -> 0.36517999 | L33: =L32/L30 -> 0.34964278 | M33: =M32/M30 -> 0.33651161
C34: Current assets | D34: Balance Sheet row 30 | E34: ='Balance Sheet'!D30 -> 28343.36 | F34: ='Balance Sheet'!E30 -> 27861.98 | G34: ='Balance Sheet'!F30 -> 30082.28 | H34: ='Balance Sheet'!G30 -> 34545.69 | I34: =I36+I59+I60+I6*($H$34-$H$36-$H$59-$H$60)/$H$6 -> 36795.031 | J34: =J36+J59+J60+J6*($H$34-$H$36-$H$59-$H$60)/$H$6 -> 39738.634 | K34: =K36+K59+K60+K6*($H$34-$H$36-$H$59-$H$60)/$H$6 -> 42520.338 | L34: =L36+L59+L60+L6*($H$34-$H$36-$H$59-$H$60)/$H$6 -> 45496.761 | M34: =M36+M59+M60+M6*($H$34-$H$36-$H$59-$H$60)/$H$6 -> 48226.567
C35: % of total assets | D35: Current assets / Total assets | E35: =E34/E30 -> 0.51309291 | F35: =F34/F30 -> 0.49537904 | G35: =G34/G30 -> 0.50669339 | H35: =H34/H30 -> 0.58546559 | I35: =I34/I30 -> 0.60068772 | J35: =J34/J30 -> 0.61899684 | K35: =K34/K30 -> 0.63482001 | L35: =L34/L30 -> 0.65035722 | M35: =M34/M30 -> 0.66348839
C36: Total cash & bank balances | D36: BS rows 24 + 25 | E36: ='Balance Sheet'!D24+'Balance Sheet'!D25 -> 6701.45 | F36: ='Balance Sheet'!E24+'Balance Sheet'!E25 -> 7153.69 | G36: ='Balance Sheet'!F24+'Balance Sheet'!F25 -> 6642.58 | H36: ='Balance Sheet'!G24+'Balance Sheet'!G25 -> 6157.47 | I36: =I6*I125 -> 7225.1767 | J36: =J6*J125 -> 7803.1908 | K36: =K6*K125 -> 8349.4142 | L36: =L6*L125 -> 8933.8732 | M36: =M6*M125 -> 9469.9055
C37: Total debt | D37: Borrowings + lease liabilities | E37: ='Balance Sheet'!D39+'Balance Sheet'!D49+'Balance Sheet'!D50 -> 4950.89 | F37: ='Balance Sheet'!E39+'Balance Sheet'!E49+'Balance Sheet'!E50 -> 4829.93 | G37: ='Balance Sheet'!F39+'Balance Sheet'!F49+'Balance Sheet'!F50 -> 5453.51 | H37: ='Balance Sheet'!G39+'Balance Sheet'!G49+'Balance Sheet'!G50 -> 8856.46 | I37: =H37*(1+I126) -> 8856.46 | J37: =I37*(1+J126) -> 8856.46 | K37: =J37*(1+K126) -> 8856.46 | L37: =K37*(1+L126) -> 8856.46 | M37: =L37*(1+M126) -> 8856.46
C38: Net cash / (debt) | D38: Total cash - total debt | E38: =E36-E37 -> 1750.56 | F38: =F36-F37 -> 2323.76 | G38: =G36-G37 -> 1189.07 | H38: =H36-H37 -> -2698.99 | I38: =I36-I37 -> -1631.2833 | J38: =J36-J37 -> -1053.2692 | K38: =K36-K37 -> -507.04584 | L38: =L36-L37 -> 77.413154 | M38: =M36-M37 -> 613.44554
C39: Total liabilities | D39: Balance Sheet row 58 | E39: ='Balance Sheet'!D58 -> 29268.21 | F39: ='Balance Sheet'!E58 -> 29737.16 | G39: ='Balance Sheet'!F58 -> 32541.75 | H39: ='Balance Sheet'!G58 -> 34566.84 | I39: =I30-I40 -> 36564.6 | J39: =J30-J40 -> 39236.484 | K39: =K30-K40 -> 41727.45 | L39: =L30-L40 -> 44392.784 | M39: =M30-M40 -> 46792.834
C40: Total equity | D40: Balance Sheet row 36 | E40: ='Balance Sheet'!D36 -> 25972 | F40: ='Balance Sheet'!E36 -> 26506.6 | G40: ='Balance Sheet'!F36 -> 26828.03 | H40: ='Balance Sheet'!G36 -> 24438.65 | I40: =H40+I26 -> 24690.241 | J40: =I40+J26 -> 24961.959 | K40: =J40+K26 -> 25252.698 | L40: =K40+L26 -> 25563.788 | M40: =L40+M26 -> 25893.544
C41: Equity growth (YoY) | D41: (Current / Prior) - 1 | F41: =F40/E40-1 -> 0.020583706 | G41: =G40/F40-1 -> 0.012126414 | H41: =H40/G40-1 -> -0.08906282 | I41: =I40/H40-1 -> 0.010294798 | J41: =J40/I40-1 -> 0.011005087 | K41: =K40/J40-1 -> 0.011647264 | L41: =L40/K40-1 -> 0.012319089 | M41: =M40/L40-1 -> 0.012899326
C42: Working capital (CA - CL) | D42: Current assets - current liabilities | E42: =E34-'Balance Sheet'!D57 -> 7986.15 | F42: =F34-'Balance Sheet'!E57 -> 6490.83 | G42: =G34-'Balance Sheet'!F57 -> 6730.84 | H42: =H34-'Balance Sheet'!G57 -> 9212.89 | I42: =I34-I6*'Balance Sheet'!$G$57/$H$6 -> 9435.607 | J42: =J34-J6*'Balance Sheet'!$G$57/$H$6 -> 10190.456 | K42: =K34-K6*'Balance Sheet'!$G$57/$H$6 -> 10903.787 | L42: =L34-L6*'Balance Sheet'!$G$57/$H$6 -> 11667.053 | M42: =M34-M6*'Balance Sheet'!$G$57/$H$6 -> 12367.076
C43: Capital employed | D43: Total assets - current liabilities | E43: =E30-'Balance Sheet'!D57 -> 34883 | F43: =F30-'Balance Sheet'!E57 -> 34872.61 | G43: =G30-'Balance Sheet'!F57 -> 36018.35 | H43: =H30-'Balance Sheet'!G57 -> 33672.7 | I43: =I30-I6*'Balance Sheet'!$G$57/$H$6 -> 33895.417 | J43: =J30-J6*'Balance Sheet'!$G$57/$H$6 -> 34650.266 | K43: =K30-K6*'Balance Sheet'!$G$57/$H$6 -> 35363.597 | L43: =L30-L6*'Balance Sheet'!$G$57/$H$6 -> 36126.863 | M43: =M30-M6*'Balance Sheet'!$G$57/$H$6 -> 36826.886
C45: 3. LIQUIDITY RATIOS
C46: Current ratio | D46: CA / CL | E46: =E34/'Balance Sheet'!D57 -> 1.3923008 | F46: =F34/'Balance Sheet'!E57 -> 1.3037193 | G46: =G34/'Balance Sheet'!F57 -> 1.2882409 | H46: =H34/'Balance Sheet'!G57 -> 1.3636744 | I46: =I34/(I6*'Balance Sheet'!$G$57/$H$6) -> 1.3448759 | J46: =J34/(J6*'Balance Sheet'!$G$57/$H$6) -> 1.3448759 | K46: =K34/(K6*'Balance Sheet'!$G$57/$H$6) -> 1.3448759 | L46: =L34/(L6*'Balance Sheet'!$G$57/$H$6) -> 1.3448759 | M46: =M34/(M6*'Balance Sheet'!$G$57/$H$6) -> 1.3448759
C47: Quick ratio | D47: (CA - Inventories) / CL | E47: =(E34-'Balance Sheet'!D21)/'Balance Sheet'!D57 -> 1.0388904 | F47: =(F34-'Balance Sheet'!E21)/'Balance Sheet'!E57 -> 0.99675357 | G47: =(G34-'Balance Sheet'!F21)/'Balance Sheet'!F57 -> 0.99892683 | H47: =(H34-'Balance Sheet'!G21)/'Balance Sheet'!G57 -> 1.0786459 | I47: =(I34-I60)/(I6*'Balance Sheet'!$G$57/$H$6) -> 1.0606372 | J47: =(J34-J60)/(J6*'Balance Sheet'!$G$57/$H$6) -> 1.0606372 | K47: =(K34-K60)/(K6*'Balance Sheet'!$G$57/$H$6) -> 1.0606372 | L47: =(L34-L60)/(L6*'Balance Sheet'!$G$57/$H$6) -> 1.0606372 | M47: =(M34-M60)/(M6*'Balance Sheet'!$G$57/$H$6) -> 1.0606372
C48: Cash ratio | D48: Total cash / CL | E48: =E36/'Balance Sheet'!D57 -> 0.32919295 | F48: =F36/'Balance Sheet'!E57 -> 0.33473585 | G48: =G36/'Balance Sheet'!F57 -> 0.28446126 | H48: =H36/'Balance Sheet'!G57 -> 0.24306314 | I48: =I36/(I6*'Balance Sheet'!$G$57/$H$6) -> 0.26408365 | J48: =J36/(J6*'Balance Sheet'!$G$57/$H$6) -> 0.26408365 | K48: =K36/(K6*'Balance Sheet'!$G$57/$H$6) -> 0.26408365 | L48: =L36/(L6*'Balance Sheet'!$G$57/$H$6) -> 0.26408365 | M48: =M36/(M6*'Balance Sheet'!$G$57/$H$6) -> 0.26408365
C49: Operating cash flow ratio | D49: CFO / CL | E49: ='Cash Flow'!D32/'Balance Sheet'!D57 -> 0.027506225 | F49: ='Cash Flow'!E32/'Balance Sheet'!E57 -> 0.030894454 | G49: ='Cash Flow'!F32/'Balance Sheet'!F57 -> -0.031754787 | H49: ='Cash Flow'!G32/'Balance Sheet'!G57 -> -0.14656493 | I49: =I81/(I6*'Balance Sheet'!$G$57/$H$6) -> 0.069133434 | J49: =J81/(J6*'Balance Sheet'!$G$57/$H$6) -> 0.015154257 | K49: =K81/(K6*'Balance Sheet'!$G$57/$H$6) -> 0.015780353 | L49: =L81/(L6*'Balance Sheet'!$G$57/$H$6) -> 0.015780353 | M49: =M81/(M6*'Balance Sheet'!$G$57/$H$6) -> 0.016418263
C51: 4. SOLVENCY & LEVERAGE
C52: Debt / Equity | D52: Total debt / total equity | E52: =E37/E40 -> 0.19062413 | F52: =F37/F40 -> 0.18221613 | G52: =G37/G40 -> 0.20327657 | H52: =H37/H40 -> 0.36239563 | I52: =I37/I40 -> 0.35870286 | J52: =J37/J40 -> 0.35479827 | K52: =K37/K40 -> 0.35071342 | L52: =L37/L40 -> 0.34644553 | M52: =M37/M40 -> 0.34203353
C53: Debt / Total assets | D53: Total debt / total assets | E53: =E37/E30 -> 0.08962475 | F53: =F37/F30 -> 0.085874949 | G53: =G37/G30 -> 0.09185665 | H53: =H37/H30 -> 0.1500955 | I53: =I37/I30 -> 0.14458384 | J53: =J37/J30 -> 0.13795443 | K53: =K37/K30 -> 0.13222515 | L53: =L37/L30 -> 0.1265994 | M53: =M37/M30 -> 0.12184484
C54: Equity multiplier | D54: Total assets / total equity | E54: =E30/E40 -> 2.126914 | F54: =F30/F40 -> 2.1218776 | G54: =G30/G40 -> 2.2129761 | H54: =H30/H40 -> 2.4144337 | I54: =I30/I40 -> 2.4809333 | J54: =J30/J40 -> 2.5718511 | K54: =K30/K40 -> 2.6523957 | L54: =L30/L40 -> 2.7365495 | M54: =M30/M40 -> 2.8071236
C55: Interest coverage | D55: EBIT / Finance costs | E55: =E19/E21 -> -8.6160717 | F55: =F19/F21 -> 2.3216654 | G55: =G19/G21 -> 1.9194715 | H55: =H19/H21 -> 1.3318246 | I55: =I19/I21 -> 1.52 | J55: =J19/J21 -> 1.52 | K55: =K19/K21 -> 1.52 | L55: =L19/L21 -> 1.52 | M55: =M19/M21 -> 1.52
C56: Debt / EBITDA | D56: Total debt / EBITDA | E56: =E37/E16 -> -1.8011554 | F56: =F37/F16 -> 4.2347748 | G56: =G37/G16 -> 4.3240301 | H56: =H37/H16 -> 7.2424745 | I56: =I37/I16 -> 6.8643548 | J56: =J37/J16 -> 6.3558841 | K56: =K37/K16 -> 5.9400786 | L56: =L37/L16 -> 5.5514753 | M56: =M37/M16 -> 5.2372408
C58: 5. ACTIVITY & EFFICIENCY
C59: Trade receivables (Current) | D59: Balance Sheet row 23 | E59: ='Balance Sheet'!D23 -> 4035.07 | F59: ='Balance Sheet'!E23 -> 3024.75 | G59: ='Balance Sheet'!F23 -> 3128.35 | H59: ='Balance Sheet'!G23 -> 4785.38 | I59: =I120/365*I6 -> 4100.3938 | J59: =J120/365*J6 -> 4428.4253 | K59: =K120/365*K6 -> 4738.4151 | L59: =L120/365*L6 -> 5070.1041 | M59: =M120/365*M6 -> 5374.3104
C60: Inventories | D60: Balance Sheet row 21 | E60: ='Balance Sheet'!D21 -> 7194.45 | F60: ='Balance Sheet'!E21 -> 6560.21 | G60: ='Balance Sheet'!F21 -> 6755.9 | H60: ='Balance Sheet'!G21 -> 7220.57 | I60: =I121/365*I6 -> 7776.6089 | J60: =J121/365*J6 -> 8398.7377 | K60: =K121/365*K6 -> 8986.6493 | L60: =L121/365*L6 -> 9615.7147 | M60: =M121/365*M6 -> 10192.658
C61: Trade payables (Current) | D61: BS rows 51 + 52 | E61: ='Balance Sheet'!D51+'Balance Sheet'!D52 -> 6680.83 | F61: ='Balance Sheet'!E51+'Balance Sheet'!E52 -> 7749.59 | G61: ='Balance Sheet'!F51+'Balance Sheet'!F52 -> 9895.83 | H61: ='Balance Sheet'!G51+'Balance Sheet'!G52 -> 8696.24 | I61: =I122/365*I6 -> 9897.5023 | J61: =J122/365*J6 -> 10689.302 | K61: =K122/365*K6 -> 11437.554 | L61: =L122/365*L6 -> 12238.182 | M61: =M122/365*M6 -> 12972.473
C62: Days Sales Outstanding (DSO) | D62: AR / Revenue * 365 | E62: =E59/E6*365 -> 85.090238 | F62: =F59/F6*365 -> 52.049836 | G62: =G59/G6*365 -> 48.870134 | H62: =H59/H6*365 -> 73.104247 | I62: =I59/I6*365 -> 58 | J62: =J59/J6*365 -> 58 | K62: =K59/K6*365 -> 58 | L62: =L59/L6*365 -> 58 | M62: =M59/M6*365 -> 58
C63: Days Inventory Outstanding (DIO) | D63: Inventories / Revenue * 365 | E63: =E60/E6*365 -> 151.71421 | F63: =F60/F6*365 -> 112.88796 | G63: =G60/G6*365 -> 105.53862 | H63: =H60/H6*365 -> 110.30563 | I63: =I60/I6*365 -> 110 | J63: =J60/J6*365 -> 110 | K63: =K60/K6*365 -> 110 | L63: =L60/L6*365 -> 110 | M63: =M60/M6*365 -> 110
C64: Days Payable Outstanding (DPO) | D64: AP / Revenue * 365 | E64: =E61/E6*365 -> 140.88316 | F64: =F61/F6*365 -> 133.35479 | G64: =G61/G6*365 -> 154.58965 | H64: =H61/H6*365 -> 132.84882 | I64: =I61/I6*365 -> 140 | J64: =J61/J6*365 -> 140 | K64: =K61/K6*365 -> 140 | L64: =L61/L6*365 -> 140 | M64: =M61/M6*365 -> 140
C65: Cash Conversion Cycle | D65: DSO + DIO - DPO | E65: =E62+E63-E64 -> 95.921289 | F65: =F62+F63-F64 -> 31.583009 | G65: =G62+G63-G64 -> -0.18089924 | H65: =H62+H63-H64 -> 50.561054 | I65: =I62+I63-I64 -> 28 | J65: =J62+J63-J64 -> 28 | K65: =K62+K63-K64 -> 28 | L65: =L62+L63-L64 -> 28 | M65: =M62+M63-M64 -> 28
C66: Asset turnover | D66: Revenue / Average assets | E66: =E6/E30 -> 0.31333498 | F66: =F6/((E30+F30)/2) -> 0.38052269 | G66: =G6/((F30+G30)/2) -> 0.40419034 | H66: =H6/((G30+H30)/2) -> 0.4036785 | I66: =I6/((H30+I30)/2) -> 0.42913902 | J66: =J6/((I30+J30)/2) -> 0.44428552 | K66: =K6/((J30+K30)/2) -> 0.45463724 | L66: =L6/((K30+L30)/2) -> 0.46600634 | M66: =M6/((L30+M30)/2) -> 0.47420628
C67: Fixed asset turnover | D67: Revenue / PP&E | E67: =E6/'Balance Sheet'!D7 -> 7.1259088 | F67: =F6/'Balance Sheet'!E7 -> 9.0787685 | G67: =G6/'Balance Sheet'!F7 -> 9.7000673 | H67: =H6/'Balance Sheet'!G7 -> 9.5164198 | I67: =I6/'Balance Sheet'!$G$7 -> 10.277733 | J67: =J6/'Balance Sheet'!$G$7 -> 11.099952 | K67: =K6/'Balance Sheet'!$G$7 -> 11.876949 | L67: =L6/'Balance Sheet'!$G$7 -> 12.708335 | M67: =M6/'Balance Sheet'!$G$7 -> 13.470835
C68: Working capital turnover | D68: Revenue / Working capital | E68: =E6/E42 -> 2.1673385 | F68: =F6/F42 -> 3.2678548 | G68: =G6/G42 -> 3.471326 | H68: =H6/H42 -> 2.5934077 | I68: =I6/I42 -> 2.7347687 | J68: =J6/J42 -> 2.7347687 | K68: =K6/K42 -> 2.7347687 | L68: =L6/L42 -> 2.7347687 | M68: =M6/M42 -> 2.7347687
C69: Working capital / Revenue | D69: Working capital / Revenue | E69: =E42/E6 -> 0.4613954 | F69: =F42/F6 -> 0.30601115 | G69: =G42/G6 -> 0.28807435 | H69: =H42/H6 -> 0.38559305 | I69: =I42/I6 -> 0.36566164 | J69: =J42/J6 -> 0.36566164 | K69: =K42/K6 -> 0.36566164 | L69: =L42/L6 -> 0.36566164 | M69: =M42/M6 -> 0.36566164
C71: 6. PROFITABILITY & RETURNS
C72: Average total assets | D72: (Opening + Closing) / 2; FY21 closing | E72: =E30 -> 55240.21 | F72: =(E30+F30)/2 -> 55741.985 | G72: =(F30+G30)/2 -> 57806.775 | H72: =(G30+H30)/2 -> 59187.645 | I72: =(H30+I30)/2 -> 60130.171 | J72: =(I30+J30)/2 -> 62726.642 | K72: =(J30+K30)/2 -> 65589.296 | L72: =(K30+L30)/2 -> 68468.36 | M72: =(L30+M30)/2 -> 71321.474
C73: Average total equity | D73: (Opening + Closing) / 2; FY21 closing | E73: =E40 -> 25972 | F73: =(E40+F40)/2 -> 26239.3 | G73: =(F40+G40)/2 -> 26667.315 | H73: =(G40+H40)/2 -> 25633.34 | I73: =(H40+I40)/2 -> 24564.445 | J73: =(I40+J40)/2 -> 24826.1 | K73: =(J40+K40)/2 -> 25107.328 | L73: =(K40+L40)/2 -> 25408.243 | M73: =(L40+M40)/2 -> 25728.666
C74: Average capital employed | D74: (Opening + Closing) / 2; FY21 closing | E74: =E43 -> 34883 | F74: =(E43+F43)/2 -> 34877.805 | G74: =(F43+G43)/2 -> 35445.48 | H74: =(G43+H43)/2 -> 34845.525 | I74: =(H43+I43)/2 -> 33784.059 | J74: =(I43+J43)/2 -> 34272.841 | K74: =(J43+K43)/2 -> 35006.932 | L74: =(K43+L43)/2 -> 35745.23 | M74: =(L43+M43)/2 -> 36476.874
C75: Return on Assets (ROA) | D75: PAT / Average assets | E75: =E26/E72 -> -0.048872008 | F75: =F26/F72 -> 0.007978008 | G75: =G26/G72 -> 0.0082583746 | H75: =H26/H72 -> 0.0047682249 | I75: =I26/I72 -> 0.0041841054 | J75: =J26/J72 -> 0.0043317838 | K75: =K26/K72 -> 0.0044327131 | L75: =L26/L72 -> 0.0045435618 | M75: =M26/M72 -> 0.0046235113
C76: Return on Equity (ROE) | D76: PAT / Average equity | E76: =E26/E73 -> -0.10394656 | F76: =F26/F73 -> 0.016948242 | G76: =G26/G73 -> 0.01790169 | H76: =H26/H73 -> 0.01100988 | I76: =I26/I73 -> 0.010242078 | J76: =J26/J73 -> 0.010944862 | K76: =K26/K73 -> 0.011579827 | L76: =L26/L73 -> 0.012243673 | M76: =M26/M73 -> 0.012816663
C77: Return on Capital Employed (ROCE) | D77: EBIT / Average capital employed | E77: =E19/E74 -> -0.092365336 | F77: =F19/F74 -> 0.023694725 | G77: =G19/G74 -> 0.028236887 | H77: =H19/H74 -> 0.027950504 | I77: =I19/I74 -> 0.029024331 | J77: =J19/J74 -> 0.030899232 | K77: =K19/K74 -> 0.032368869 | L77: =L19/L74 -> 0.033919329 | M77: =M19/M74 -> 0.035233322
C78: Return on Sales (ROS) | D78: EBIT / Revenue | E78: =E19/E6 -> -0.18614811 | F78: =F19/F6 -> 0.038961694 | G78: =G19/G6 -> 0.042836404 | H78: =H19/H6 -> 0.04076336 | I78: =I19/I6 -> 0.038 | J78: =J19/J6 -> 0.038 | K78: =K19/K6 -> 0.038 | L78: =L19/L6 -> 0.038 | M78: =M19/M6 -> 0.038
C80: 7. CASH FLOW ANALYSIS
C81: Operating cash flow (CFO) | D81: Cash Flow row 32 | E81: ='Cash Flow'!D32 -> 559.95 | F81: ='Cash Flow'!E32 -> 660.25 | G81: ='Cash Flow'!F32 -> -741.52 | H81: ='Cash Flow'!G32 -> -3712.9 | I81: =I26+I18-((I59-H59)+(I60-H60)-(I61-H61)) -> 1891.4509 | J81: =J26+J18-((J59-I59)+(J60-I60)-(J61-I61)) -> 447.78068 | K81: =K26+K18-((K59-J59)+(K60-J60)-(K61-J61)) -> 498.92033 | L81: =L26+L18-((L59-K59)+(L60-K60)-(L61-K61)) -> 533.84475 | M81: =M26+M18-((M59-L59)+(M60-L60)-(M61-L61)) -> 588.75055
C82: CFO / Revenue | D82: CFO / Revenue | E82: =E81/E6 -> 0.032350802 | F82: =F81/F6 -> 0.031127585 | G82: =G81/G6 -> -0.031736439 | H82: =H81/H6 -> -0.15539841 | I82: =I81/I6 -> 0.073300113 | J82: =J81/J6 -> 0.016067605 | K82: =K81/K6 -> 0.016731436 | L82: =L81/L6 -> 0.016731436 | M82: =M81/M6 -> 0.017407793
C83: CFO / Net income | D83: CFO / PAT (cash earnings quality) | E83: =E81/E26 -> -0.20741193 | F83: =F81/F26 -> 1.4846754 | G83: =G81/G26 -> -1.5532793 | H83: =H81/H26 -> -13.156048 | I83: =I81/I26 -> 7.5179603 | J83: =J81/J26 -> 1.6479595 | K83: =K81/K26 -> 1.7160448 | L83: =L81/L26 -> 1.7160448 | M83: =M81/M26 -> 1.7854146
C84: Capital expenditure | D84: Cash Flow row 40 (absolute) | E84: =-'Cash Flow'!D40 -> 250.35 | F84: =-'Cash Flow'!E40 -> 169.38 | G84: =-'Cash Flow'!F40 -> 188.4 | H84: =-'Cash Flow'!G40 -> 232.5 | I84: =I6*I128 -> 258.04202 | J84: =J6*J128 -> 278.68539 | K84: =K6*K128 -> 298.19336 | L84: =L6*L128 -> 319.0669 | M84: =M6*M128 -> 338.21091
C85: Free cash flow (FCF) | D85: CFO - Capex | E85: =E81-E84 -> 309.6 | F85: =F81-F84 -> 490.87 | G85: =G81-G84 -> -929.92 | H85: =H81-H84 -> -3945.4 | I85: =I81-I84 -> 1633.4089 | J85: =J81-J84 -> 169.09529 | K85: =K81-K84 -> 200.72697 | L85: =L81-L84 -> 214.77785 | M85: =M81-M84 -> 250.53963
C86: FCF / Revenue | D86: FCF / Revenue | E86: =E85/E6 -> 0.017886969 | F86: =F85/F6 -> 0.023142139 | G86: =G85/G6 -> -0.039799803 | H86: =H85/H6 -> -0.16512938 | I86: =I85/I6 -> 0.063300113 | J86: =J85/J6 -> 0.0060676053 | K86: =K85/K6 -> 0.0067314364 | L86: =L85/L6 -> 0.0067314364 | M86: =M85/M6 -> 0.0074077927
C87: Investing cash flow | D87: Cash Flow row 41 | E87: ='Cash Flow'!D41 -> -42.5 | F87: ='Cash Flow'!E41 -> -1125.32 | G87: ='Cash Flow'!F41 -> 1480.46 | H87: ='Cash Flow'!G41 -> 1330.86 | I87: =-I84 -> -258.04202 | J87: =-J84 -> -278.68539 | K87: =-K84 -> -298.19336 | L87: =-L84 -> -319.0669 | M87: =-M84 -> -338.21091
C88: Financing cash flow | D88: Cash Flow row 48 | E88: ='Cash Flow'!D48 -> -394.15 | F88: ='Cash Flow'!E48 -> -329.49 | G88: ='Cash Flow'!F48 -> 88.96 | H88: ='Cash Flow'!G48 -> 2655.74 | I88: =I37-H37 -> 0 | J88: =J37-I37 -> 0 | K88: =K37-J37 -> 0 | L88: =L37-K37 -> 0 | M88: =M37-L37 -> 0
C89: Net change in cash | D89: Cash Flow row 49 | E89: ='Cash Flow'!D49 -> 123.3 | F89: ='Cash Flow'!E49 -> -794.56 | G89: ='Cash Flow'!F49 -> 827.9 | H89: ='Cash Flow'!G49 -> 273.7 | I89: =I81+I87+I88 -> 1633.4089 | J89: =J81+J87+J88 -> 169.09529 | K89: =K81+K87+K88 -> 200.72697 | L89: =L81+L87+L88 -> 214.77785 | M89: =M81+M87+M88 -> 250.53963
C90: Capex / Revenue | D90: Capex / Revenue | E90: =E84/E6 -> 0.014463833 | F90: =F84/F6 -> 0.0079854453 | G90: =G84/G6 -> 0.0080633633 | H90: =H84/H6 -> 0.0097309731 | I90: =I84/I6 -> 0.01 | J90: =J84/J6 -> 0.01 | K90: =K84/K6 -> 0.01 | L90: =L84/L6 -> 0.01 | M90: =M84/M6 -> 0.01
C91: Capex / Depreciation | D91: Capex / D&A (reinvestment ratio) | E91: =E84/E18 -> 0.52900158 | F91: =F84/F18 -> 0.53922068 | G91: =G84/G18 -> 0.72366905 | H91: =H84/H18 -> 0.93411008 | I91: =I84/I18 -> 0.83333333 | J91: =J84/J18 -> 0.83333333 | K91: =K84/K18 -> 0.83333333 | L91: =L84/L18 -> 0.83333333 | M91: =M84/M18 -> 0.83333333
C93: 8. GROWTH METRICS (YoY)
C94: Revenue growth | D94: P&L row 6 YoY | F94: =F6/E6-1 -> 0.225459 | G94: =G6/F6-1 -> 0.10154358 | H94: =H6/G6-1 -> 0.022591113 | I94: =I6/H6-1 -> 0.08 | J94: =J6/I6-1 -> 0.08 | K94: =K6/J6-1 -> 0.07 | L94: =L6/K6-1 -> 0.07 | M94: =M6/L6-1 -> 0.06
C95: Gross profit growth | D95: Gross profit YoY | F95: =F12/E12-1 -> 0.18006238 | G95: =G12/F12-1 -> 0.10081733 | H95: =H12/G12-1 -> 0.0030364287 | I95: =I12/H12-1 -> 0.092523462 | J95: =J12/I12-1 -> 0.08 | K95: =K12/J12-1 -> 0.07 | L95: =L12/K12-1 -> 0.07 | M95: =M12/L12-1 -> 0.06
C96: EBITDA growth | D96: EBITDA YoY | F96: =F16/E16-1 -> -1.4149334 | G96: =G16/F16-1 -> 0.10580076 | H96: =H16/G16-1 -> -0.030415236 | I96: =I16/H16-1 -> 0.055084532 | J96: =J16/I16-1 -> 0.08 | K96: =K16/J16-1 -> 0.07 | L96: =L16/K16-1 -> 0.07 | M96: =M16/L16-1 -> 0.06
C97: EBIT growth | D97: EBIT YoY | F97: =F19/E19-1 -> -1.2564945 | G97: =G19/F19-1 -> 0.21109121 | H97: =H19/G19-1 -> -0.0268966 | I97: =I19/H19-1 -> 0.006786479 | J97: =J19/I19-1 -> 0.08 | K97: =K19/J19-1 -> 0.07 | L97: =L19/K19-1 -> 0.07 | M97: =M19/L19-1 -> 0.06
C98: PAT growth | D98: PAT YoY (n/a if prior-year loss) | F98: ="n/a" -> n/a | G98: =G26/F26-1 -> 0.073486092 | H98: =H26/G26-1 -> -0.40882716 | I98: =I26/H26-1 -> -0.1085289 | J98: =J26/I26-1 -> 0.08 | K98: =K26/J26-1 -> 0.07 | L98: =L26/K26-1 -> 0.07 | M98: =M26/L26-1 -> 0.06
C99: Total assets growth | D99: BS row 31 YoY | F99: =F30/E30-1 -> 0.01816702 | G99: =G30/F30-1 -> 0.055580032 | H99: =H30/G30-1 -> -0.0061359489 | I99: =I30/H30-1 -> 0.03812087 | J99: =J30/I30-1 -> 0.048055018 | K99: =K30/J30-1 -> 0.043329779 | L99: =L30/K30-1 -> 0.0444374 | M99: =M30/L30-1 -> 0.039021433
C100: Equity growth | D100: BS row 36 YoY | F100: =F40/E40-1 -> 0.020583706 | G100: =G40/F40-1 -> 0.012126414 | H100: =H40/G40-1 -> -0.08906282 | I100: =I40/H40-1 -> 0.010294798 | J100: =J40/I40-1 -> 0.011005087 | K100: =K40/J40-1 -> 0.011647264 | L100: =L40/K40-1 -> 0.012319089 | M100: =M40/L40-1 -> 0.012899326
C101: Revenue CAGR FY21-FY24 | D101: 3-year CAGR | H101: =(H6/E6)^(1/3)-1 -> 0.11344173
C102: Total income CAGR FY21-FY24 | D102: 3-year CAGR | H102: =(H9/E9)^(1/3)-1 -> 0.1144354
C103: Assets CAGR FY21-FY24 | D103: 3-year CAGR | H103: =(H30/E30)^(1/3)-1 -> 0.02222318
C105: 9. FORECAST ASSUMPTIONS (FY2025E-FY2029E)
C107: Growth Driver
C108: Revenue growth (% YoY) | D108: Manual input - drives revenue forecast | I108: 0.08 | J108: 0.08 | K108: 0.07 | L108: 0.07 | M108: 0.06
C110: Margins (% of Revenue)
C111: Gross margin | D111: FY22-FY24 avg: 30.1% | I111: 0.3 | J111: 0.3 | K111: 0.3 | L111: 0.3 | M111: 0.3
...

Sheet Dashboard
B1: BHEL | FINANCIAL DASHBOARD
B2: Bharat Heavy Electricals Limited - Consolidated FY2021-FY2024 (₹ Crore)
Y3: =MATCH($C$4,$Y$4:$Y$7,0) -> 4
B4: ▶ SPOTLIGHT YEAR: | C4: FY2024 | E4: ◀ Change the cell to update all KPI tiles. Type FY2021, FY2022, FY2023, or FY2024. | Y4: FY2021
Y5: FY2022
B6: REVENUE | G6: EBITDA | L6: PROFIT AFTER TAX | Q6: FREE CASH FLOW | Y6: FY2023
B7: =$C$4 & " | ₹ Crore" -> FY2024 | ₹ Crore | G7: =$C$4 & " | ₹ Crore" -> FY2024 | ₹ Crore | L7: =$C$4 & " | ₹ Crore" -> FY2024 | ₹ Crore | Q7: =$C$4 & " | ₹ Crore" -> FY2024 | ₹ Crore | Y7: FY2024
B8: {=INDEX('Detailed Analysis'!$E$6:$H$6,$Y$3)} -> 23892.78 | G8: {=INDEX('Detailed Analysis'!$E$16:$H$16,$Y$3)} -> 1222.85 | L8: {=INDEX('Detailed Analysis'!$E$26:$H$26,$Y$3)} -> 282.22 | Q8: {=INDEX('Detailed Analysis'!$E$85:$H$85,$Y$3)} -> -3945.4
B9: {=IFERROR((INDEX('Detailed Analysis'!$E$6:$H$6,$Y$3)-INDEX('Detailed Analysis'!$E$6:$H$6,$Y$3-1))/ABS(INDEX('Detailed Analysis'!$E$6:$H$6,$Y$3-1)),"")} -> 0.022591113 | G9: {=IFERROR((INDEX('Detailed Analysis'!$E$16:$H$16,$Y$3)-INDEX('Detailed Analysis'!$E$16:$H$16,$Y$3-1))/ABS(INDEX('Detailed Analysis'!$E$16:$H$16,$Y$3-1)),"")} -> -0.030415236 | L9: {=IFERROR((INDEX('Detailed Analysis'!$E$26:$H$26,$Y$3)-INDEX('Detailed Analysis'!$E$26:$H$26,$Y$3-1))/ABS(INDEX('Detailed Analysis'!$E$26:$H$26,$Y$3-1)),"")} -> -0.40882716 | Q9: {=IFERROR(INDEX('Detailed Analysis'!$E$85:$H$85,$Y$3)-INDEX('Detailed Analysis'!$E$85:$H$85,$Y$3-1),"")} -> -3015.48
Y10: — helper data (hidden axis) —
B11: NET CASH / (DEBT) | G11: RETURN ON EQUITY | L11: CURRENT RATIO | Q11: DEBT / EBITDA | Z11: FY2021 | AA11: FY2022 | AB11: FY2023 | AC11: FY2024
B12: =$C$4 & " | ₹ Crore" -> FY2024 | ₹ Crore | G12: =$C$4 & " | ROE" -> FY2024 | ROE | L12: =$C$4 & " | Liquidity" -> FY2024 | Liquidity | Q12: =$C$4 & " | Leverage (lower is better)" -> FY2024 | Leverage (lower is better) | Y12: Revenue | Z12: ='Detailed Analysis'!E6 -> 17308.69 | AA12: ='Detailed Analysis'!F6 -> 21211.09 | AB12: ='Detailed Analysis'!G6 -> 23364.94 | AC12: ='Detailed Analysis'!H6 -> 23892.78
B13: {=INDEX('Detailed Analysis'!$E$38:$H$38,$Y$3)} -> -2698.99 | G13: {=INDEX('Detailed Analysis'!$E$76:$H$76,$Y$3)} -> 0.01100988 | L13: {=INDEX('Detailed Analysis'!$E$46:$H$46,$Y$3)} -> 1.3636744 | Q13: {=INDEX('Detailed Analysis'!$E$56:$H$56,$Y$3)} -> 7.2424745 | Y13: EBITDA | Z13: ='Detailed Analysis'!E16 -> -2748.73 | AA13: ='Detailed Analysis'!F16 -> 1140.54 | AB13: ='Detailed Analysis'!G16 -> 1261.21 | AC13: ='Detailed Analysis'!H16 -> 1222.85
B14: {=IFERROR(INDEX('Detailed Analysis'!$E$38:$H$38,$Y$3)-INDEX('Detailed Analysis'!$E$38:$H$38,$Y$3-1),"")} -> -3888.06 | G14: {=IFERROR(INDEX('Detailed Analysis'!$E$76:$H$76,$Y$3)-INDEX('Detailed Analysis'!$E$76:$H$76,$Y$3-1),"")} -> -0.0068918097 | L14: {=IFERROR(INDEX('Detailed Analysis'!$E$46:$H$46,$Y$3)-INDEX('Detailed Analysis'!$E$46:$H$46,$Y$3-1),"")} -> 0.07543347 | Q14: {=IFERROR(INDEX('Detailed Analysis'!$E$56:$H$56,$Y$3)-INDEX('Detailed Analysis'!$E$56:$H$56,$Y$3-1),"")} -> 2.9184444 | Y14: PAT | Z14: ='Detailed Analysis'!E26 -> -2699.7 | AA14: ='Detailed Analysis'!F26 -> 444.71 | AB14: ='Detailed Analysis'!G26 -> 477.39 | AC14: ='Detailed Analysis'!H26 -> 282.22
Y15: EBITDA margin | Z15: ='Detailed Analysis'!E17 -> -0.15880636 | AA15: ='Detailed Analysis'!F17 -> 0.053770928 | AB15: ='Detailed Analysis'!G17 -> 0.053978739 | AC15: ='Detailed Analysis'!H17 -> 0.051180733
B16: 4-YEAR TRENDS | ALL FIGURES IN ₹ CRORE UNLESS NOTED | Y16: PAT margin | Z16: ='Detailed Analysis'!E27 -> -0.15597368 | AA16: ='Detailed Analysis'!F27 -> 0.020965919 | AB16: ='Detailed Analysis'!G27 -> 0.020431895 | AC16: ='Detailed Analysis'!H27 -> 0.011811936
Y17: Gross margin | Z17: ='Detailed Analysis'!E13 -> 0.31418091 | AA17: ='Detailed Analysis'!F13 -> 0.30254221 | AB17: ='Detailed Analysis'!G13 -> 0.30234274 | AC17: ='Detailed Analysis'!H13 -> 0.29656114
Y18: CFO | Z18: ='Detailed Analysis'!E81 -> 559.95 | AA18: ='Detailed Analysis'!F81 -> 660.25 | AB18: ='Detailed Analysis'!G81 -> -741.52 | AC18: ='Detailed Analysis'!H81 -> -3712.9
Y19: Investing CF | Z19: ='Detailed Analysis'!E87 -> -42.5 | AA19: ='Detailed Analysis'!F87 -> -1125.32 | AB19: ='Detailed Analysis'!G87 -> 1480.46 | AC19: ='Detailed Analysis'!H87 -> 1330.86
Y20: Financing CF | Z20: ='Detailed Analysis'!E88 -> -394.15 | AA20: ='Detailed Analysis'!F88 -> -329.49 | AB20: ='Detailed Analysis'!G88 -> 88.96 | AC20: ='Detailed Analysis'!H88 -> 2655.74
Y21: FCF | Z21: ='Detailed Analysis'!E85 -> 309.6 | AA21: ='Detailed Analysis'!F85 -> 490.87 | AB21: ='Detailed Analysis'!G85 -> -929.92 | AC21: ='Detailed Analysis'!H85 -> -3945.4
Y22: Total cash | Z22: ='Detailed Analysis'!E36 -> 6701.45 | AA22: ='Detailed Analysis'!F36 -> 7153.69 | AB22: ='Detailed Analysis'!G36 -> 6642.58 | AC22: ='Detailed Analysis'!H36 -> 6157.47
Y23: Total debt | Z23: ='Detailed Analysis'!E37 -> 4950.89 | AA23: ='Detailed Analysis'!F37 -> 4829.93 | AB23: ='Detailed Analysis'!G37 -> 5453.51 | AC23: ='Detailed Analysis'!H37 -> 8856.46
Y24: Net cash/(debt) | Z24: ='Detailed Analysis'!E38 -> 1750.56 | AA24: ='Detailed Analysis'!F38 -> 2323.76 | AB24: ='Detailed Analysis'!G38 -> 1189.07 | AC24: ='Detailed Analysis'!H38 -> -2698.99
Y25: Total equity | Z25: ='Detailed Analysis'!E40 -> 25972 | AA25: ='Detailed Analysis'!F40 -> 26506.6 | AB25: ='Detailed Analysis'!G40 -> 26828.03 | AC25: ='Detailed Analysis'!H40 -> 24438.65
Y26: Current ratio | Z26: ='Detailed Analysis'!E46 -> 1.3923008 | AA26: ='Detailed Analysis'!F46 -> 1.3037193 | AB26: ='Detailed Analysis'!G46 -> 1.2882409 | AC26: ='Detailed Analysis'!H46 -> 1.3636744
Y27: Quick ratio | Z27: ='Detailed Analysis'!E47 -> 1.0388904 | AA27: ='Detailed Analysis'!F47 -> 0.99675357 | AB27: ='Detailed Analysis'!G47 -> 0.99892683 | AC27: ='Detailed Analysis'!H47 -> 1.0786459
Y28: Cash ratio | Z28: ='Detailed Analysis'!E48 -> 0.32919295 | AA28: ='Detailed Analysis'!F48 -> 0.33473585 | AB28: ='Detailed Analysis'!G48 -> 0.28446126 | AC28: ='Detailed Analysis'!H48 -> 0.24306314
Y29: D/E | Z29: ='Detailed Analysis'!E52 -> 0.19062413 | AA29: ='Detailed Analysis'!F52 -> 0.18221613 | AB29: ='Detailed Analysis'!G52 -> 0.20327657 | AC29: ='Detailed Analysis'!H52 -> 0.36239563
Y30: Debt/EBITDA | Z30: ='Detailed Analysis'!E56 -> -1.8011554 | AA30: ='Detailed Analysis'!F56 -> 4.2347748 | AB30: ='Detailed Analysis'!G56 -> 4.3240301 | AC30: ='Detailed Analysis'!H56 -> 7.2424745
Y31: DSO | Z31: ='Detailed Analysis'!E62 -> 85.090238 | AA31: ='Detailed Analysis'!F62 -> 52.049836 | AB31: ='Detailed Analysis'!G62 -> 48.870134 | AC31: ='Detailed Analysis'!H62 -> 73.104247
Y32: DIO | Z32: ='Detailed Analysis'!E63 -> 151.71421 | AA32: ='Detailed Analysis'!F63 -> 112.88796 | AB32: ='Detailed Analysis'!G63 -> 105.53862 | AC32: ='Detailed Analysis'!H63 -> 110.30563
Y33: DPO | Z33: ='Detailed Analysis'!E64 -> 140.88316 | AA33: ='Detailed Analysis'!F64 -> 133.35479 | AB33: ='Detailed Analysis'!G64 -> 154.58965 | AC33: ='Detailed Analysis'!H64 -> 132.84882
Y34: CCC | Z34: ='Detailed Analysis'!E65 -> 95.921289 | AA34: ='Detailed Analysis'!F65 -> 31.583009 | AB34: ='Detailed Analysis'!G65 -> -0.18089924 | AC34: ='Detailed Analysis'!H65 -> 50.561054
Y35: ROA | Z35: ='Detailed Analysis'!E75 -> -0.048872008 | AA35: ='Detailed Analysis'!F75 -> 0.007978008 | AB35: ='Detailed Analysis'!G75 -> 0.0082583746 | AC35: ='Detailed Analysis'!H75 -> 0.0047682249
Y36: ROE | Z36: ='Detailed Analysis'!E76 -> -0.10394656 | AA36: ='Detailed Analysis'!F76 -> 0.016948242 | AB36: ='Detailed Analysis'!G76 -> 0.01790169 | AC36: ='Detailed Analysis'!H76 -> 0.01100988
Y37: ROCE | Z37: ='Detailed Analysis'!E77 -> -0.092365336 | AA37: ='Detailed Analysis'!F77 -> 0.023694725 | AB37: ='Detailed Analysis'!G77 -> 0.028236887 | AC37: ='Detailed Analysis'!H77 -> 0.027950504
B40: KEY OBSERVATIONS | FY2021 → FY2024
B62: INSIGHTS & RECOMMENDATIONS
B63: ↑ STRENGTH | Operational Recovery | H63: ↓ RISK | Cash Flow Reversal | N63: ↓ RISK | Leverage Inflection
B64: Revenue rebuilt from ₹17,309 Cr (FY21) to ₹23,893 Cr (FY24) at 11.3% CAGR; EBITDA turned from a (2,749) loss to +1,223; PAT positive every year since FY22. The operational engine is functioning despite cyclical headwinds. | H64: Operating cash flow swung from +₹660 Cr (FY22) to (₹3,713) Cr (FY24). FCF deteriorated to (₹3,945) Cr. The deterioration is concentrated in working capital - receivables built ₹2,469 Cr and contract assets continue expanding, signalling slower collections on long-cycle projects. | N64: Net position moved from net cash of ₹1,189 Cr (FY23) to net debt of (₹2,699) Cr (FY24). Total debt grew 78% YoY to ₹8,857 Cr - short-term borrowings funding working capital. Debt / EBITDA at 7.24x is materially stretched for an engineering business.
B66: → WATCH | Margin Compression | H66: → WATCH | Return Profile Weak | N66: ↑ STRENGTH | Liquidity Cushion
B67: Gross margin contracted from 31.4% (FY21) to 29.7% (FY24); EBITDA margin at 5.1% remains structurally thin. Material and direct-cost intensity is rising while finance costs nearly doubled - from ₹374 Cr (FY21) to ₹731 Cr (FY24). | H67: ROE at 1.1% and ROCE at 2.8% (FY24) are well below cost of capital. Asset turnover at 0.40x reflects heavy non-current assets (deferred tax, long-term receivables) that are not generating proportional revenue. | N67: Current ratio of 1.36x and quick ratio of 1.08x remain above 1.0x. Total cash & bank balances of ₹6,157 Cr in FY24 still provide a meaningful buffer even after the leverage build.
B69: ■ RECOMMENDED ACTIONS | Working Capital | H69: ■ RECOMMENDED ACTIONS | Capital Structure | N69: ■ RECOMMENDED ACTIONS | Margin Restoration
B70: Tighten collections discipline - DSO rose from 49 to 73 days; review project milestone-billing terms. Consider receivables factoring/securitization to release tied-up cash and reduce reliance on short-term borrowings. | H70: Term out short-term borrowings into longer-tenor debt to better match long-cycle project assets. Re-establish a net cash buffer through asset monetisation (long-term receivables, surplus land) to reduce Debt/EBITDA below 3.0x. | N70: Renegotiate input contracts and review pricing on long-cycle orders booked at outdated cost assumptions. Track project-level margin to identify drag from legacy orders. Target EBITDA margin of 8-10% by FY26.
B72: NOTE
B73: All figures are pulled live from the Detailed Analysis sheet. Change the Spotlight Year cell (C4) to refresh the KPI tiles. Source statements: P&L, Balance Sheet, Cash Flow. Currency: INR Crore unless otherwise noted.

Sheet __tracelight_scratchpad__
